published/__init__.py
published/admin.py
published/apps.py
published/constants.py
published/mixins.py
published/models.py
published/utils.py
published/tests/__init__.py
published/tests/models.py
published/tests/settings.py
published/tests/test_article.py
published/tests/test_views.py
published/tests/urls.py
django_published-0.8.0.dist-info/LICENSE
django_published-0.8.0.dist-info/WHEEL
django_published-0.8.0.dist-info/METADATA
django_published-0.8.0.dist-info/RECORD
