Metadata-Version: 2.1
Name: django-published
Version: 0.8.0
Summary: Control public visibility of model instances.
Home-page: https://github.com/dmptrluke/django-published
Author: Luke Rogers
Author-email: luke@dmptr.com
Requires-Python: >=3.8
Classifier: Programming Language :: Python :: 3
Classifier: Programming Language :: Python :: 3.8
Classifier: Programming Language :: Python :: 3.9
Classifier: Programming Language :: Python :: 3.10
Classifier: Programming Language :: Python :: 3.11
Classifier: Development Status :: 4 - Beta
Classifier: Framework :: Django
Classifier: Intended Audience :: Developers
Classifier: License :: OSI Approved :: MIT License
Classifier: Operating System :: OS Independent
Requires-Dist: django>=3.2
Requires-Dist: dataclasses; python_version == "3.6"
Requires-Dist: flake8 ; extra == "test"
Requires-Dist: coverage ; extra == "test"
Requires-Dist: mock ; extra == "test"
Provides-Extra: test
